gwcatalog/ET.py
gwcatalog/GWTC.py
gwcatalog/IO.py
gwcatalog/LIGO.py
gwcatalog/LISA.py
gwcatalog/__init__.py
gwcatalog/auxiliary.py
gwcatalog/cosmology.py
gwcatalog/plot.py
gwcatalog-1.2.0.data/scripts/gwc
gwcatalog-1.2.0.dist-info/LICENSE.md
gwcatalog-1.2.0.dist-info/METADATA
gwcatalog-1.2.0.dist-info/WHEEL
gwcatalog-1.2.0.dist-info/top_level.txt
gwcatalog-1.2.0.dist-info/RECORD
