Metadata-Version: 2.1
Name: gwcatalog
Version: 1.2.0
Summary: Generate catalogs of standard siren events.
Home-page: https://github.com/jpmvferreira/gwcatalog
Author: José Ferreira
Author-email: jose@jpferreira.me
License: MIT
Platform: UNKNOWN
License-File: LICENSE.md
Requires-Dist: numpy
Requires-Dist: scipy
Requires-Dist: matplotlib
Requires-Dist: pandas
